[
    {
        "id":1,
        "name":"Renz",
        "surname":"Halagao",
        "email":"halagao@gmail.com", 
        "phone": "0911111111111",
        "salary":"25.01" 
    },
    {
        "id":2,
        "name":"Lester",
        "surname":"Jallorina",
        "email":"Lester@gmail.com", 
        "phone": "092324422222",
        "salary":"24.99" 
    },
    {
        "id":3,
        "name":"Jerone Daniel",
        "surname":"Halagao",
        "email":"Jerone@gmail.com", 
        "phone": "09999999999",
        "salary":"27.00" 
    },
    {
        "id":4,
        "name":"Gerald",
        "surname":"Halagao",
        "email":"Gerald@gmail.com", 
        "phone": "09000010000",
        "salary":"25.03" 
    }
]